genshinpyrail/genshinpyrail.py
genshinpyrail/src/data/ascension/monster_en.json
genshinpyrail/src/data/ascension/monster_ru.json
genshinpyrail/src/data/help.json
genshinpyrail/src/font/comforta.ttf
genshinpyrail/src/font/Genshin_Impact.ttf
genshinpyrail/src/generation/genshin/generator_ascension.py
genshinpyrail/src/generation/genshin/generator_character_list.py
genshinpyrail/src/generation/genshin/generator_tcg.py
genshinpyrail/src/generation/genshin/generator_tcg_info.py
genshinpyrail/src/generation/honkai/generator_ascension.py
genshinpyrail/src/generation/honkai/generator_character_list.py
genshinpyrail/src/tools/genryrail_error.py
genshinpyrail/src/tools/git_file.py
genshinpyrail/src/tools/model.py
genshinpyrail/src/tools/pill.py
genshinpyrail/src/tools/update_data.py
genshinpyrail/src/tools/utility.py
genshinpyrail-0.0.4.dist-info/METADATA
genshinpyrail-0.0.4.dist-info/WHEEL
genshinpyrail-0.0.4.dist-info/RECORD
